cxx_VSCL/DigitalHuman.py
cxx_VSCL/Public.py
cxx_VSCL/Robot.py
cxx_VSCL/UAV.py
cxx_VSCL/__init__.py
cxx_VSCL/core.py
cxx_VSCL-1.3.dist-info/METADATA
cxx_VSCL-1.3.dist-info/WHEEL
cxx_VSCL-1.3.dist-info/top_level.txt
cxx_VSCL-1.3.dist-info/RECORD
