Metadata-Version: 2.1
Name: cxx-VSCL
Version: 1.3
Summary: 深职院虚仿
Requires-Dist: websocket-client ==1.5.2
